LICENSE
MANIFEST.in
README.rst
ez_setup.py
setup.py
pytff/__init__.py
pytff/constants.py
pytff/core.py
pytff/test.py
pytff.egg-info/PKG-INFO
pytff.egg-info/SOURCES.txt
pytff.egg-info/dependency_links.txt
pytff.egg-info/requires.txt
pytff.egg-info/top_level.txt
pytff/datasets/__init__.py
pytff/datasets/__init__.pyc
pytff/datasets/__pycache__/__init__.cpython-35.pyc
pytff/datasets/big_period/_info.txt
pytff/datasets/big_period/dff.dat
pytff/datasets/big_period/match.dat
pytff/datasets/big_period/star.dat
pytff/datasets/big_period/target.lis
pytff/datasets/big_period/temp.dat
pytff/datasets/big_period/template.dat
pytff/datasets/big_period/tff.dat
pytff/datasets/big_period/tff.par
pytff/datasets/single_dat/_info.txt
pytff/datasets/single_dat/dff.dat
pytff/datasets/single_dat/match.dat
pytff/datasets/single_dat/ogle.dat
pytff/datasets/single_dat/target.lis
pytff/datasets/single_dat/template.dat
pytff/datasets/single_dat/tff.dat
pytff/datasets/single_dat/tff.par
pytff/datasets/split_dat/_info.txt
pytff/datasets/split_dat/dff.dat
pytff/datasets/split_dat/match.dat
pytff/datasets/split_dat/ogle_0.dat
pytff/datasets/split_dat/ogle_1.dat
pytff/datasets/split_dat/target.lis
pytff/datasets/split_dat/temp.dat
pytff/datasets/split_dat/template.dat
pytff/datasets/split_dat/tff.dat
pytff/datasets/split_dat/tff.par