Metadata-Version: 1.1
Name: pytff
Version: 0.8
Summary: Wrapper arround G. Kovacs & G. Kupi Template Fourier Fitting
Home-page: https://github.com/carpyncho/pytff
Author: Juan BC
Author-email: jbc.develop@gmail.com
License: 3 Clause BSD
Keywords: tff fourier template match
Platform: UNKNOWN
Classifier: Development Status :: 4 - Beta
Classifier: Intended Audience :: Education
Classifier: Intended Audience :: Science/Research
Classifier: License :: OSI Approved :: BSD License
Classifier: Operating System :: OS Independent
Classifier: Programming Language :: Python
Classifier: Programming Language :: Python :: 2
Classifier: Programming Language :: Python :: 2.7
Classifier: Programming Language :: Python :: 3
Classifier: Programming Language :: Python :: 3.4
Classifier: Programming Language :: Python :: Implementation :: CPython
Classifier: Topic :: Scientific/Engineering
Classifier: Topic :: Scientific/Engineering :: Physics
Classifier: Topic :: Scientific/Engineering :: Astronomy
